heframework/__init__.py
heframework/src/__init__.py
heframework/src/choose_return.py
heframework/src/list_json.py
heframework/src/list_list.py
heframework/src/refresh.py
heframework/src/show.py
heframework-0.5.1.dist-info/LICENSE
heframework-0.5.1.dist-info/METADATA
heframework-0.5.1.dist-info/WHEEL
heframework-0.5.1.dist-info/top_level.txt
heframework-0.5.1.dist-info/RECORD
