Metadata-Version: 2.1
Name: heframework
Version: 0.5.1
Summary: 本次更新: 修复choose在json模式下返回None的错误
Home-page: https://gitee.com/hestudio-framework/main-windows/
Author: heStudio
Author-email: heStudio <hestudio@hestudio.org>
Project-URL: Homepage, https://gitee.com/hestudio-framework/main-windows/
Project-URL: Bug Tracker, https://www.hestudio.org/get-help
Project-URL: Blog, https://www.hestudio.org/
Classifier: Programming Language :: Python :: 3
Classifier: License :: OSI Approved :: MIT License
Classifier: Natural Language :: Chinese (Simplified)
Classifier: Environment :: Win32 (MS Windows)
Requires-Python: >=3.6
License-File: LICENSE
